geofstpkg/__init__.py
geofstpkg/common.py
geofstpkg/geofstpkg.py
geofstpkg-0.0.1.dist-info/LICENSE
geofstpkg-0.0.1.dist-info/METADATA
geofstpkg-0.0.1.dist-info/WHEEL
geofstpkg-0.0.1.dist-info/entry_points.txt
geofstpkg-0.0.1.dist-info/top_level.txt
geofstpkg-0.0.1.dist-info/RECORD
